hello6tr41/__init__.py
hello6tr41/circle.py
hello6tr41/types.py
hello6tr41/util.py
hello6tr41/version.py
hello6tr41-0.0.5.dist-info/licenses/LICENSE
hello6tr41-0.0.5.dist-info/METADATA
hello6tr41-0.0.5.dist-info/WHEEL
hello6tr41-0.0.5.dist-info/top_level.txt
hello6tr41-0.0.5.dist-info/RECORD
