Metadata-Version: 2.4
Name: hello6tr41
Version: 0.0.5
Summary: nana
Author-email: Ahmed <ahmed@example.com>
License: 
License-File: LICENSE
Dynamic: license-file
